table_parser/__init__.py
table_parser/table_parser.py
bbd_table_parser-0.0.1.dist-info/LICENSE
bbd_table_parser-0.0.1.dist-info/METADATA
bbd_table_parser-0.0.1.dist-info/WHEEL
bbd_table_parser-0.0.1.dist-info/top_level.txt
bbd_table_parser-0.0.1.dist-info/RECORD
