Metadata-Version: 2.1
Name: bbd-table-parser
Version: 0.0.1
Summary: Package to parse inline tables for use with pytest-bdd.
Home-page: https://gitlab.com/GreatIrishElk/table_parse
Author: Simon Murphy
Author-email: murphysimon@outlook.com
License: UNKNOWN
Platform: UNKNOWN
Classifier: Programming Language :: Python :: 3
Classifier: License :: OSI Approved :: MIT License
Classifier: Operating System :: OS Independent
Requires-Python: >=3.6
